proxy3.py
proxy3-0.2.1.dist-info/LICENSE
proxy3-0.2.1.dist-info/METADATA
proxy3-0.2.1.dist-info/WHEEL
proxy3-0.2.1.dist-info/entry_points.txt
proxy3-0.2.1.dist-info/top_level.txt
proxy3-0.2.1.dist-info/RECORD
