Metadata-Version: 2.1
Name: proxy3
Version: 0.2.1
Summary: Proxy3 - Man-in-the-middle http/https proxy in a single python script
Author-email: Yifei Kong <kong@yifei.me>
License: Copyright (c) 2015, inaz2
Project-URL: repository, https://github.com/yifeikong/proxy3
Classifier: Development Status :: 5 - Production/Stable
Classifier: Intended Audience :: Developers
Classifier: License :: OSI Approved :: BSD License
Classifier: Programming Language :: Python :: 3
Classifier: Programming Language :: Python :: 3.9
Classifier: Programming Language :: Python :: 3.10
Classifier: Programming Language :: Python :: 3.11
Requires-Python: >=3.8
License-File: LICENSE
